crashlog.py
crashlog-0.1.0.dist-info/METADATA
crashlog-0.1.0.dist-info/WHEEL
crashlog-0.1.0.dist-info/top_level.txt
crashlog-0.1.0.dist-info/RECORD
