Metadata-Version: 2.1
Name: crashlog
Version: 0.1.0
Summary: Log & email uncaught exceptions
Home-page: https://github.com/tebeka/crashlog
Author: Miki Tebeka
Author-email: miki.tebeka@gmail.com
License: MIT
Platform: UNKNOWN
Classifier: Development Status :: 4 - Beta
Classifier: Intended Audience :: Developers
Classifier: License :: OSI Approved :: MIT License
Classifier: Programming Language :: Python
Classifier: Programming Language :: Python :: 2
Classifier: Programming Language :: Python :: 3
Classifier: Topic :: Software Development :: Libraries
Classifier: Topic :: Software Development :: Libraries :: Python Modules
